alldefconfig.py
allmodconfig.py
allnoconfig.py
allyesconfig.py
defconfig.py
genconfig.py
guiconfig.py
kconfiglib.py
listnewconfig.py
menuconfig.py
oldconfig.py
olddefconfig.py
savedefconfig.py
setconfig.py
kconfiglib-14.1.0.dist-info/LICENSE.txt
kconfiglib-14.1.0.dist-info/METADATA
kconfiglib-14.1.0.dist-info/WHEEL
kconfiglib-14.1.0.dist-info/entry_points.txt
kconfiglib-14.1.0.dist-info/top_level.txt
kconfiglib-14.1.0.dist-info/RECORD
