Metadata-Version: 1.2
Name: kconfiglib
Version: 14.1.0
Summary: A flexible Python Kconfig implementation
Home-page: https://github.com/ulfalizer/Kconfiglib
Author: Ulf "Ulfalizer" Magnusson
Author-email: ulfalizer@gmail.com
License: ISC
Project-URL: GitHub repository, https://github.com/ulfalizer/Kconfiglib
Project-URL: Examples, https://github.com/ulfalizer/Kconfiglib/tree/master/examples
Keywords: kconfig,kbuild,menuconfig,configuration-management
Platform: UNKNOWN
Classifier: Development Status :: 5 - Production/Stable
Classifier: Intended Audience :: Developers
Classifier: Topic :: Software Development :: Build Tools
Classifier: Topic :: System :: Operating System Kernels :: Linux
Classifier: License :: OSI Approved :: ISC License (ISCL)
Classifier: Operating System :: POSIX
Classifier: Operating System :: Microsoft :: Windows
Classifier: Programming Language :: Python :: 2
Classifier: Programming Language :: Python :: 2.7
Classifier: Programming Language :: Python :: 3
Classifier: Programming Language :: Python :: 3.2
Classifier: Programming Language :: Python :: 3.3
Classifier: Programming Language :: Python :: 3.4
Classifier: Programming Language :: Python :: 3.5
Classifier: Programming Language :: Python :: 3.6
Classifier: Programming Language :: Python :: 3.7
Classifier: Programming Language :: Python :: 3.8
Classifier: Programming Language :: Python :: Implementation :: CPython
Classifier: Programming Language :: Python :: Implementation :: PyPy
Requires-Python: >=2.7,!=3.0.*,!=3.1.*
